{"singlePage": [], "startSite": "", "filingNum": "", "onePageListNum": 15, "commentLabelColor": "#006b75", "yearColorList": ["#bc4c00", "#0969da", "#1f883d", "#A333D0"], "i18n": "CN", "themeMode": "manual", "dayTheme": "light", "nightTheme": "dark", "urlMode": "pinyin", "script": "", "style": "", "head": "", "indexScript": "", "indexStyle": "", "bottomText": "", "showPostSource": 1, "iconList": {}, "UTC": 8, "rssSplit": "sentence", "exlink": {}, "needComment": 1, "allHead": "", "title": "\u9ebb\u74dc\u7684\u535a\u5ba2", "subTitle": "\u8fdb\u51fb\u7684\u5927\u4e00\u5c0f\u4e1c\u897f", "avatarUrl": "https://img2.baidu.com/it/u=3812130406,3092278595&fm=253&fmt=auto&app=138&f=JPEG?w=380&h=372", "GMEEK_VERSION": "last", "postListJson": {"P1": {"htmlDir": "docs/post/IVG.html", "labels": ["documentation"], "postTitle": "IVG", "postUrl": "post/IVG.html", "postSourceUrl": "https://github.com/Mug-p/Mug-p.github.io/issues/1", "commentNum": 0, "wordCount": 11, "description": "Hello world\u3002", "top": 0, "createdAt": 1758900971, "style": "", "script": "", "head": "", "ogImage": "https://img2.baidu.com/it/u=3812130406,3092278595&fm=253&fmt=auto&app=138&f=JPEG?w=380&h=372", "createdDate": "2025-09-26", "dateLabelColor": "#0969da"}}, "singeListJson": {}, "labelColorDict": {"bug": "#d73a4a", "documentation": "#0075ca", "duplicate": "#cfd3d7", "enhancement": "#a2eeef", "good first issue": "#7057ff", "help wanted": "#008672", "invalid": "#e4e669", "question": "#d876e3", "wontfix": "#ffffff"}, "displayTitle": "\u9ebb\u74dc\u7684\u535a\u5ba2", "faviconUrl": "https://img2.baidu.com/it/u=3812130406,3092278595&fm=253&fmt=auto&app=138&f=JPEG?w=380&h=372", "ogImage": "https://img2.baidu.com/it/u=3812130406,3092278595&fm=253&fmt=auto&app=138&f=JPEG?w=380&h=372", "primerCSS": "<link href='https://mirrors.sustech.edu.cn/cdnjs/ajax/libs/Primer/21.0.7/primer.css' rel='stylesheet' />", "homeUrl": "https://Mug-p.github.io", "prevUrl": "disabled", "nextUrl": "disabled"}